{
  "AGLT2_site_0:AGLT2_site_1": {
    "bandwidth": "104.38Mbps",
    "latency": "17ms"
  },
  "AGLT2_site_0:AGLT2_site_2": {
    "bandwidth": "84.06Mbps",
    "latency": "38ms"
  },
  "AGLT2_site_0:AGLT2_site_3": {
    "bandwidth": "105.07Mbps",
    "latency": "7ms"
  },
  "AGLT2_site_0:AGLT2_site_4": {
    "bandwidth": "100.15Mbps",
    "latency": "2ms"
  },
  "AGLT2_site_0:AGLT2_site_5": {
    "bandwidth": "44.88Mbps",
    "latency": "5ms"
  },
  "AGLT2_site_0:AGLT2_site_6": {
    "bandwidth": "53.53Mbps",
    "latency": "28ms"
  },
  "AGLT2_site_0:AGLT2_site_7": {
    "bandwidth": "78.39Mbps",
    "latency": "17ms"
  },
  "AGLT2_site_0:AGLT2_site_8": {
    "bandwidth": "148.67Mbps",
    "latency": "18ms"
  },
  "AGLT2_site_0:AGLT2_site_9": {
    "bandwidth": "80.27Mbps",
    "latency": "16ms"
  },
  "AGLT2_site_0:AGLT2_site_10": {
    "bandwidth": "126.99Mbps",
    "latency": "25ms"
  },
  "AGLT2_site_0:AGLT2_site_11": {
    "bandwidth": "117.75Mbps",
    "latency": "14ms"
  },
  "AGLT2_site_0:AGLT2_site_12": {
    "bandwidth": "44.61Mbps",
    "latency": "4ms"
  },
  "AGLT2_site_0:AGLT2_site_13": {
    "bandwidth": "50.83Mbps",
    "latency": "27ms"
  },
  "AGLT2_site_0:AGLT2_site_14": {
    "bandwidth": "109.92Mbps",
    "latency": "4ms"
  },
  "AGLT2_site_0:AGLT2_site_15": {
    "bandwidth": "103.5Mbps",
    "latency": "39ms"
  },
  "AGLT2_site_0:AGLT2_site_16": {
    "bandwidth": "30.38Mbps",
    "latency": "17ms"
  },
  "AGLT2_site_0:AGLT2_site_17": {
    "bandwidth": "87.05Mbps",
    "latency": "2ms"
  },
  "AGLT2_site_0:AGLT2_site_18": {
    "bandwidth": "71.1Mbps",
    "latency": "37ms"
  },
  "AGLT2_site_0:AGLT2_site_19": {
    "bandwidth": "128.82Mbps",
    "latency": "16ms"
  },
  "AGLT2_site_0:AGLT2_site_20": {
    "bandwidth": "67.32Mbps",
    "latency": "24ms"
  },
  "AGLT2_site_0:AGLT2_site_21": {
    "bandwidth": "121.41Mbps",
    "latency": "15ms"
  },
  "AGLT2_site_0:AGLT2_site_22": {
    "bandwidth": "152.51Mbps",
    "latency": "35ms"
  },
  "AGLT2_site_0:AGLT2_site_23": {
    "bandwidth": "52.39Mbps",
    "latency": "8ms"
  },
  "AGLT2_site_0:AGLT2_site_24": {
    "bandwidth": "118.21Mbps",
    "latency": "35ms"
  },
  "AGLT2_site_0:AGLT2_site_25": {
    "bandwidth": "150.88Mbps",
    "latency": "2ms"
  },
  "AGLT2_site_0:AGLT2_site_26": {
    "bandwidth": "94.04Mbps",
    "latency": "35ms"
  },
  "AGLT2_site_0:AGLT2_site_27": {
    "bandwidth": "95.99Mbps",
    "latency": "17ms"
  },
  "AGLT2_site_0:AGLT2_site_28": {
    "bandwidth": "62.06Mbps",
    "latency": "20ms"
  },
  "AGLT2_site_0:AGLT2_site_29": {
    "bandwidth": "20.7Mbps",
    "latency": "34ms"
  },
  "AGLT2_site_0:AGLT2_site_30": {
    "bandwidth": "70.61Mbps",
    "latency": "36ms"
  },
  "AGLT2_site_0:AGLT2_site_31": {
    "bandwidth": "86.87Mbps",
    "latency": "39ms"
  },
  "AGLT2_site_1:AGLT2_site_2": {
    "bandwidth": "98.94Mbps",
    "latency": "17ms"
  },
  "AGLT2_site_1:AGLT2_site_3": {
    "bandwidth": "0.1Mbps",
    "latency": "9ms"
  },
  "AGLT2_site_1:AGLT2_site_4": {
    "bandwidth": "88.3Mbps",
    "latency": "18ms"
  },
  "AGLT2_site_1:AGLT2_site_5": {
    "bandwidth": "94.35Mbps",
    "latency": "20ms"
  },
  "AGLT2_site_1:AGLT2_site_6": {
    "bandwidth": "200.4Mbps",
    "latency": "34ms"
  },
  "AGLT2_site_1:AGLT2_site_7": {
    "bandwidth": "21.69Mbps",
    "latency": "30ms"
  },
  "AGLT2_site_1:AGLT2_site_8": {
    "bandwidth": "99.85Mbps",
    "latency": "35ms"
  },
  "AGLT2_site_1:AGLT2_site_9": {
    "bandwidth": "195.19Mbps",
    "latency": "2ms"
  },
  "AGLT2_site_1:AGLT2_site_10": {
    "bandwidth": "135.52Mbps",
    "latency": "5ms"
  },
  "AGLT2_site_1:AGLT2_site_11": {
    "bandwidth": "23.21Mbps",
    "latency": "40ms"
  },
  "AGLT2_site_1:AGLT2_site_12": {
    "bandwidth": "31.22Mbps",
    "latency": "17ms"
  },
  "AGLT2_site_1:AGLT2_site_13": {
    "bandwidth": "111.8Mbps",
    "latency": "5ms"
  },
  "AGLT2_site_1:AGLT2_site_14": {
    "bandwidth": "167.75Mbps",
    "latency": "22ms"
  },
  "AGLT2_site_1:AGLT2_site_15": {
    "bandwidth": "71.08Mbps",
    "latency": "27ms"
  },
  "AGLT2_site_1:AGLT2_site_16": {
    "bandwidth": "115.61Mbps",
    "latency": "5ms"
  },
  "AGLT2_site_1:AGLT2_site_17": {
    "bandwidth": "87.35Mbps",
    "latency": "15ms"
  },
  "AGLT2_site_1:AGLT2_site_18": {
    "bandwidth": "32.71Mbps",
    "latency": "20ms"
  },
  "AGLT2_site_1:AGLT2_site_19": {
    "bandwidth": "134.32Mbps",
    "latency": "15ms"
  },
  "AGLT2_site_1:AGLT2_site_20": {
    "bandwidth": "146.77Mbps",
    "latency": "19ms"
  },
  "AGLT2_site_1:AGLT2_site_21": {
    "bandwidth": "81.21Mbps",
    "latency": "13ms"
  },
  "AGLT2_site_1:AGLT2_site_22": {
    "bandwidth": "76.66Mbps",
    "latency": "37ms"
  },
  "AGLT2_site_1:AGLT2_site_23": {
    "bandwidth": "119.14Mbps",
    "latency": "1ms"
  },
  "AGLT2_site_1:AGLT2_site_24": {
    "bandwidth": "99.16Mbps",
    "latency": "29ms"
  },
  "AGLT2_site_1:AGLT2_site_25": {
    "bandwidth": "50.77Mbps",
    "latency": "34ms"
  },
  "AGLT2_site_1:AGLT2_site_26": {
    "bandwidth": "165.86Mbps",
    "latency": "9ms"
  },
  "AGLT2_site_1:AGLT2_site_27": {
    "bandwidth": "166.09Mbps",
    "latency": "33ms"
  },
  "AGLT2_site_1:AGLT2_site_28": {
    "bandwidth": "84.92Mbps",
    "latency": "15ms"
  },
  "AGLT2_site_1:AGLT2_site_29": {
    "bandwidth": "187.61Mbps",
    "latency": "4ms"
  },
  "AGLT2_site_1:AGLT2_site_30": {
    "bandwidth": "0.1Mbps",
    "latency": "33ms"
  },
  "AGLT2_site_1:AGLT2_site_31": {
    "bandwidth": "153.89Mbps",
    "latency": "1ms"
  },
  "AGLT2_site_2:AGLT2_site_3": {
    "bandwidth": "107.72Mbps",
    "latency": "39ms"
  },
  "AGLT2_site_2:AGLT2_site_4": {
    "bandwidth": "161.36Mbps",
    "latency": "25ms"
  },
  "AGLT2_site_2:AGLT2_site_5": {
    "bandwidth": "36.12Mbps",
    "latency": "25ms"
  },
  "AGLT2_site_2:AGLT2_site_6": {
    "bandwidth": "151.42Mbps",
    "latency": "14ms"
  },
  "AGLT2_site_2:AGLT2_site_7": {
    "bandwidth": "185.67Mbps",
    "latency": "35ms"
  },
  "AGLT2_site_2:AGLT2_site_8": {
    "bandwidth": "110.44Mbps",
    "latency": "36ms"
  },
  "AGLT2_site_2:AGLT2_site_9": {
    "bandwidth": "132.27Mbps",
    "latency": "20ms"
  },
  "AGLT2_site_2:AGLT2_site_10": {
    "bandwidth": "170.22Mbps",
    "latency": "15ms"
  },
  "AGLT2_site_2:AGLT2_site_11": {
    "bandwidth": "104.76Mbps",
    "latency": "21ms"
  },
  "AGLT2_site_2:AGLT2_site_12": {
    "bandwidth": "111.67Mbps",
    "latency": "39ms"
  },
  "AGLT2_site_2:AGLT2_site_13": {
    "bandwidth": "135.52Mbps",
    "latency": "25ms"
  },
  "AGLT2_site_2:AGLT2_site_14": {
    "bandwidth": "58.41Mbps",
    "latency": "14ms"
  },
  "AGLT2_site_2:AGLT2_site_15": {
    "bandwidth": "199.21Mbps",
    "latency": "32ms"
  },
  "AGLT2_site_2:AGLT2_site_16": {
    "bandwidth": "178.65Mbps",
    "latency": "20ms"
  },
  "AGLT2_site_2:AGLT2_site_17": {
    "bandwidth": "73.32Mbps",
    "latency": "34ms"
  },
  "AGLT2_site_2:AGLT2_site_18": {
    "bandwidth": "138.8Mbps",
    "latency": "10ms"
  },
  "AGLT2_site_2:AGLT2_site_19": {
    "bandwidth": "82.84Mbps",
    "latency": "32ms"
  },
  "AGLT2_site_2:AGLT2_site_20": {
    "bandwidth": "134.43Mbps",
    "latency": "26ms"
  },
  "AGLT2_site_2:AGLT2_site_21": {
    "bandwidth": "130.54Mbps",
    "latency": "18ms"
  },
  "AGLT2_site_2:AGLT2_site_22": {
    "bandwidth": "90.04Mbps",
    "latency": "19ms"
  },
  "AGLT2_site_2:AGLT2_site_23": {
    "bandwidth": "102.12Mbps",
    "latency": "29ms"
  },
  "AGLT2_site_2:AGLT2_site_24": {
    "bandwidth": "226.65Mbps",
    "latency": "20ms"
  },
  "AGLT2_site_2:AGLT2_site_25": {
    "bandwidth": "165.74Mbps",
    "latency": "36ms"
  },
  "AGLT2_site_2:AGLT2_site_26": {
    "bandwidth": "141.67Mbps",
    "latency": "7ms"
  },
  "AGLT2_site_2:AGLT2_site_27": {
    "bandwidth": "90.67Mbps",
    "latency": "1ms"
  },
  "AGLT2_site_2:AGLT2_site_28": {
    "bandwidth": "67.39Mbps",
    "latency": "10ms"
  },
  "AGLT2_site_2:AGLT2_site_29": {
    "bandwidth": "56.29Mbps",
    "latency": "27ms"
  },
  "AGLT2_site_2:AGLT2_site_30": {
    "bandwidth": "0.1Mbps",
    "latency": "33ms"
  },
  "AGLT2_site_2:AGLT2_site_31": {
    "bandwidth": "56.94Mbps",
    "latency": "7ms"
  },
  "AGLT2_site_3:AGLT2_site_4": {
    "bandwidth": "156.37Mbps",
    "latency": "22ms"
  },
  "AGLT2_site_3:AGLT2_site_5": {
    "bandwidth": "177.51Mbps",
    "latency": "28ms"
  },
  "AGLT2_site_3:AGLT2_site_6": {
    "bandwidth": "157.0Mbps",
    "latency": "25ms"
  },
  "AGLT2_site_3:AGLT2_site_7": {
    "bandwidth": "63.82Mbps",
    "latency": "14ms"
  },
  "AGLT2_site_3:AGLT2_site_8": {
    "bandwidth": "194.75Mbps",
    "latency": "14ms"
  },
  "AGLT2_site_3:AGLT2_site_9": {
    "bandwidth": "174.67Mbps",
    "latency": "7ms"
  },
  "AGLT2_site_3:AGLT2_site_10": {
    "bandwidth": "62.34Mbps",
    "latency": "12ms"
  },
  "AGLT2_site_3:AGLT2_site_11": {
    "bandwidth": "8.77Mbps",
    "latency": "6ms"
  },
  "AGLT2_site_3:AGLT2_site_12": {
    "bandwidth": "162.0Mbps",
    "latency": "4ms"
  },
  "AGLT2_site_3:AGLT2_site_13": {
    "bandwidth": "213.6Mbps",
    "latency": "4ms"
  },
  "AGLT2_site_3:AGLT2_site_14": {
    "bandwidth": "128.81Mbps",
    "latency": "40ms"
  },
  "AGLT2_site_3:AGLT2_site_15": {
    "bandwidth": "35.78Mbps",
    "latency": "13ms"
  },
  "AGLT2_site_3:AGLT2_site_16": {
    "bandwidth": "46.73Mbps",
    "latency": "19ms"
  },
  "AGLT2_site_3:AGLT2_site_17": {
    "bandwidth": "52.37Mbps",
    "latency": "11ms"
  },
  "AGLT2_site_3:AGLT2_site_18": {
    "bandwidth": "145.38Mbps",
    "latency": "16ms"
  },
  "AGLT2_site_3:AGLT2_site_19": {
    "bandwidth": "125.46Mbps",
    "latency": "29ms"
  },
  "AGLT2_site_3:AGLT2_site_20": {
    "bandwidth": "60.57Mbps",
    "latency": "20ms"
  },
  "AGLT2_site_3:AGLT2_site_21": {
    "bandwidth": "86.64Mbps",
    "latency": "3ms"
  },
  "AGLT2_site_3:AGLT2_site_22": {
    "bandwidth": "102.1Mbps",
    "latency": "11ms"
  },
  "AGLT2_site_3:AGLT2_site_23": {
    "bandwidth": "224.95Mbps",
    "latency": "14ms"
  },
  "AGLT2_site_3:AGLT2_site_24": {
    "bandwidth": "0.1Mbps",
    "latency": "7ms"
  },
  "AGLT2_site_3:AGLT2_site_25": {
    "bandwidth": "88.41Mbps",
    "latency": "5ms"
  },
  "AGLT2_site_3:AGLT2_site_26": {
    "bandwidth": "127.42Mbps",
    "latency": "30ms"
  },
  "AGLT2_site_3:AGLT2_site_27": {
    "bandwidth": "39.53Mbps",
    "latency": "8ms"
  },
  "AGLT2_site_3:AGLT2_site_28": {
    "bandwidth": "95.06Mbps",
    "latency": "26ms"
  },
  "AGLT2_site_3:AGLT2_site_29": {
    "bandwidth": "0.1Mbps",
    "latency": "30ms"
  },
  "AGLT2_site_3:AGLT2_site_30": {
    "bandwidth": "86.39Mbps",
    "latency": "2ms"
  },
  "AGLT2_site_3:AGLT2_site_31": {
    "bandwidth": "114.63Mbps",
    "latency": "32ms"
  },
  "AGLT2_site_4:AGLT2_site_5": {
    "bandwidth": "199.53Mbps",
    "latency": "27ms"
  },
  "AGLT2_site_4:AGLT2_site_6": {
    "bandwidth": "177.07Mbps",
    "latency": "34ms"
  },
  "AGLT2_site_4:AGLT2_site_7": {
    "bandwidth": "80.05Mbps",
    "latency": "16ms"
  },
  "AGLT2_site_4:AGLT2_site_8": {
    "bandwidth": "151.26Mbps",
    "latency": "21ms"
  },
  "AGLT2_site_4:AGLT2_site_9": {
    "bandwidth": "115.11Mbps",
    "latency": "11ms"
  },
  "AGLT2_site_4:AGLT2_site_10": {
    "bandwidth": "0.1Mbps",
    "latency": "21ms"
  },
  "AGLT2_site_4:AGLT2_site_11": {
    "bandwidth": "16.81Mbps",
    "latency": "6ms"
  },
  "AGLT2_site_4:AGLT2_site_12": {
    "bandwidth": "161.78Mbps",
    "latency": "28ms"
  },
  "AGLT2_site_4:AGLT2_site_13": {
    "bandwidth": "39.91Mbps",
    "latency": "35ms"
  },
  "AGLT2_site_4:AGLT2_site_14": {
    "bandwidth": "91.05Mbps",
    "latency": "11ms"
  },
  "AGLT2_site_4:AGLT2_site_15": {
    "bandwidth": "178.79Mbps",
    "latency": "28ms"
  },
  "AGLT2_site_4:AGLT2_site_16": {
    "bandwidth": "177.48Mbps",
    "latency": "40ms"
  },
  "AGLT2_site_4:AGLT2_site_17": {
    "bandwidth": "57.24Mbps",
    "latency": "19ms"
  },
  "AGLT2_site_4:AGLT2_site_18": {
    "bandwidth": "83.76Mbps",
    "latency": "32ms"
  },
  "AGLT2_site_4:AGLT2_site_19": {
    "bandwidth": "63.71Mbps",
    "latency": "38ms"
  },
  "AGLT2_site_4:AGLT2_site_20": {
    "bandwidth": "188.41Mbps",
    "latency": "20ms"
  },
  "AGLT2_site_4:AGLT2_site_21": {
    "bandwidth": "121.68Mbps",
    "latency": "37ms"
  },
  "AGLT2_site_4:AGLT2_site_22": {
    "bandwidth": "118.88Mbps",
    "latency": "31ms"
  },
  "AGLT2_site_4:AGLT2_site_23": {
    "bandwidth": "105.98Mbps",
    "latency": "23ms"
  },
  "AGLT2_site_4:AGLT2_site_24": {
    "bandwidth": "24.42Mbps",
    "latency": "34ms"
  },
  "AGLT2_site_4:AGLT2_site_25": {
    "bandwidth": "115.12Mbps",
    "latency": "28ms"
  },
  "AGLT2_site_4:AGLT2_site_26": {
    "bandwidth": "85.03Mbps",
    "latency": "5ms"
  },
  "AGLT2_site_4:AGLT2_site_27": {
    "bandwidth": "48.91Mbps",
    "latency": "15ms"
  },
  "AGLT2_site_4:AGLT2_site_28": {
    "bandwidth": "1.63Mbps",
    "latency": "17ms"
  },
  "AGLT2_site_4:AGLT2_site_29": {
    "bandwidth": "64.0Mbps",
    "latency": "26ms"
  },
  "AGLT2_site_4:AGLT2_site_30": {
    "bandwidth": "43.33Mbps",
    "latency": "4ms"
  },
  "AGLT2_site_4:AGLT2_site_31": {
    "bandwidth": "77.56Mbps",
    "latency": "23ms"
  },
  "AGLT2_site_5:AGLT2_site_6": {
    "bandwidth": "131.41Mbps",
    "latency": "23ms"
  },
  "AGLT2_site_5:AGLT2_site_7": {
    "bandwidth": "126.23Mbps",
    "latency": "31ms"
  },
  "AGLT2_site_5:AGLT2_site_8": {
    "bandwidth": "68.13Mbps",
    "latency": "14ms"
  },
  "AGLT2_site_5:AGLT2_site_9": {
    "bandwidth": "57.66Mbps",
    "latency": "33ms"
  },
  "AGLT2_site_5:AGLT2_site_10": {
    "bandwidth": "42.24Mbps",
    "latency": "17ms"
  },
  "AGLT2_site_5:AGLT2_site_11": {
    "bandwidth": "111.41Mbps",
    "latency": "16ms"
  },
  "AGLT2_site_5:AGLT2_site_12": {
    "bandwidth": "89.85Mbps",
    "latency": "32ms"
  },
  "AGLT2_site_5:AGLT2_site_13": {
    "bandwidth": "108.2Mbps",
    "latency": "21ms"
  },
  "AGLT2_site_5:AGLT2_site_14": {
    "bandwidth": "171.88Mbps",
    "latency": "33ms"
  },
  "AGLT2_site_5:AGLT2_site_15": {
    "bandwidth": "38.28Mbps",
    "latency": "27ms"
  },
  "AGLT2_site_5:AGLT2_site_16": {
    "bandwidth": "98.36Mbps",
    "latency": "23ms"
  },
  "AGLT2_site_5:AGLT2_site_17": {
    "bandwidth": "146.03Mbps",
    "latency": "27ms"
  },
  "AGLT2_site_5:AGLT2_site_18": {
    "bandwidth": "119.42Mbps",
    "latency": "18ms"
  },
  "AGLT2_site_5:AGLT2_site_19": {
    "bandwidth": "69.3Mbps",
    "latency": "28ms"
  },
  "AGLT2_site_5:AGLT2_site_20": {
    "bandwidth": "112.54Mbps",
    "latency": "21ms"
  },
  "AGLT2_site_5:AGLT2_site_21": {
    "bandwidth": "168.77Mbps",
    "latency": "31ms"
  },
  "AGLT2_site_5:AGLT2_site_22": {
    "bandwidth": "52.73Mbps",
    "latency": "38ms"
  },
  "AGLT2_site_5:AGLT2_site_23": {
    "bandwidth": "231.76Mbps",
    "latency": "34ms"
  },
  "AGLT2_site_5:AGLT2_site_24": {
    "bandwidth": "5.72Mbps",
    "latency": "18ms"
  },
  "AGLT2_site_5:AGLT2_site_25": {
    "bandwidth": "1.41Mbps",
    "latency": "22ms"
  },
  "AGLT2_site_5:AGLT2_site_26": {
    "bandwidth": "89.78Mbps",
    "latency": "24ms"
  },
  "AGLT2_site_5:AGLT2_site_27": {
    "bandwidth": "106.52Mbps",
    "latency": "37ms"
  },
  "AGLT2_site_5:AGLT2_site_28": {
    "bandwidth": "21.07Mbps",
    "latency": "25ms"
  },
  "AGLT2_site_5:AGLT2_site_29": {
    "bandwidth": "98.97Mbps",
    "latency": "40ms"
  },
  "AGLT2_site_5:AGLT2_site_30": {
    "bandwidth": "129.28Mbps",
    "latency": "27ms"
  },
  "AGLT2_site_5:AGLT2_site_31": {
    "bandwidth": "143.9Mbps",
    "latency": "23ms"
  },
  "AGLT2_site_6:AGLT2_site_7": {
    "bandwidth": "39.82Mbps",
    "latency": "23ms"
  },
  "AGLT2_site_6:AGLT2_site_8": {
    "bandwidth": "148.01Mbps",
    "latency": "35ms"
  },
  "AGLT2_site_6:AGLT2_site_9": {
    "bandwidth": "123.76Mbps",
    "latency": "33ms"
  },
  "AGLT2_site_6:AGLT2_site_10": {
    "bandwidth": "186.56Mbps",
    "latency": "8ms"
  },
  "AGLT2_site_6:AGLT2_site_11": {
    "bandwidth": "108.43Mbps",
    "latency": "34ms"
  },
  "AGLT2_site_6:AGLT2_site_12": {
    "bandwidth": "51.55Mbps",
    "latency": "33ms"
  },
  "AGLT2_site_6:AGLT2_site_13": {
    "bandwidth": "108.52Mbps",
    "latency": "32ms"
  },
  "AGLT2_site_6:AGLT2_site_14": {
    "bandwidth": "73.84Mbps",
    "latency": "25ms"
  },
  "AGLT2_site_6:AGLT2_site_15": {
    "bandwidth": "62.79Mbps",
    "latency": "36ms"
  },
  "AGLT2_site_6:AGLT2_site_16": {
    "bandwidth": "74.77Mbps",
    "latency": "21ms"
  },
  "AGLT2_site_6:AGLT2_site_17": {
    "bandwidth": "67.68Mbps",
    "latency": "37ms"
  },
  "AGLT2_site_6:AGLT2_site_18": {
    "bandwidth": "115.19Mbps",
    "latency": "40ms"
  },
  "AGLT2_site_6:AGLT2_site_19": {
    "bandwidth": "93.31Mbps",
    "latency": "29ms"
  },
  "AGLT2_site_6:AGLT2_site_20": {
    "bandwidth": "0.1Mbps",
    "latency": "31ms"
  },
  "AGLT2_site_6:AGLT2_site_21": {
    "bandwidth": "67.0Mbps",
    "latency": "3ms"
  },
  "AGLT2_site_6:AGLT2_site_22": {
    "bandwidth": "63.09Mbps",
    "latency": "19ms"
  },
  "AGLT2_site_6:AGLT2_site_23": {
    "bandwidth": "161.35Mbps",
    "latency": "4ms"
  },
  "AGLT2_site_6:AGLT2_site_24": {
    "bandwidth": "104.0Mbps",
    "latency": "31ms"
  },
  "AGLT2_site_6:AGLT2_site_25": {
    "bandwidth": "134.04Mbps",
    "latency": "37ms"
  },
  "AGLT2_site_6:AGLT2_site_26": {
    "bandwidth": "40.21Mbps",
    "latency": "24ms"
  },
  "AGLT2_site_6:AGLT2_site_27": {
    "bandwidth": "77.26Mbps",
    "latency": "40ms"
  },
  "AGLT2_site_6:AGLT2_site_28": {
    "bandwidth": "147.79Mbps",
    "latency": "36ms"
  },
  "AGLT2_site_6:AGLT2_site_29": {
    "bandwidth": "72.84Mbps",
    "latency": "39ms"
  },
  "AGLT2_site_6:AGLT2_site_30": {
    "bandwidth": "81.34Mbps",
    "latency": "31ms"
  },
  "AGLT2_site_6:AGLT2_site_31": {
    "bandwidth": "7.19Mbps",
    "latency": "8ms"
  },
  "AGLT2_site_7:AGLT2_site_8": {
    "bandwidth": "113.84Mbps",
    "latency": "3ms"
  },
  "AGLT2_site_7:AGLT2_site_9": {
    "bandwidth": "73.1Mbps",
    "latency": "29ms"
  },
  "AGLT2_site_7:AGLT2_site_10": {
    "bandwidth": "148.87Mbps",
    "latency": "3ms"
  },
  "AGLT2_site_7:AGLT2_site_11": {
    "bandwidth": "104.73Mbps",
    "latency": "28ms"
  },
  "AGLT2_site_7:AGLT2_site_12": {
    "bandwidth": "136.84Mbps",
    "latency": "34ms"
  },
  "AGLT2_site_7:AGLT2_site_13": {
    "bandwidth": "26.33Mbps",
    "latency": "17ms"
  },
  "AGLT2_site_7:AGLT2_site_14": {
    "bandwidth": "185.84Mbps",
    "latency": "31ms"
  },
  "AGLT2_site_7:AGLT2_site_15": {
    "bandwidth": "37.73Mbps",
    "latency": "39ms"
  },
  "AGLT2_site_7:AGLT2_site_16": {
    "bandwidth": "70.71Mbps",
    "latency": "24ms"
  },
  "AGLT2_site_7:AGLT2_site_17": {
    "bandwidth": "210.71Mbps",
    "latency": "12ms"
  },
  "AGLT2_site_7:AGLT2_site_18": {
    "bandwidth": "125.28Mbps",
    "latency": "11ms"
  },
  "AGLT2_site_7:AGLT2_site_19": {
    "bandwidth": "101.98Mbps",
    "latency": "9ms"
  },
  "AGLT2_site_7:AGLT2_site_20": {
    "bandwidth": "209.7Mbps",
    "latency": "27ms"
  },
  "AGLT2_site_7:AGLT2_site_21": {
    "bandwidth": "131.15Mbps",
    "latency": "21ms"
  },
  "AGLT2_site_7:AGLT2_site_22": {
    "bandwidth": "128.5Mbps",
    "latency": "1ms"
  },
  "AGLT2_site_7:AGLT2_site_23": {
    "bandwidth": "168.82Mbps",
    "latency": "33ms"
  },
  "AGLT2_site_7:AGLT2_site_24": {
    "bandwidth": "191.02Mbps",
    "latency": "35ms"
  },
  "AGLT2_site_7:AGLT2_site_25": {
    "bandwidth": "196.84Mbps",
    "latency": "19ms"
  },
  "AGLT2_site_7:AGLT2_site_26": {
    "bandwidth": "139.71Mbps",
    "latency": "25ms"
  },
  "AGLT2_site_7:AGLT2_site_27": {
    "bandwidth": "99.97Mbps",
    "latency": "31ms"
  },
  "AGLT2_site_7:AGLT2_site_28": {
    "bandwidth": "147.05Mbps",
    "latency": "8ms"
  },
  "AGLT2_site_7:AGLT2_site_29": {
    "bandwidth": "0.1Mbps",
    "latency": "29ms"
  },
  "AGLT2_site_7:AGLT2_site_30": {
    "bandwidth": "88.91Mbps",
    "latency": "1ms"
  },
  "AGLT2_site_7:AGLT2_site_31": {
    "bandwidth": "122.36Mbps",
    "latency": "22ms"
  },
  "AGLT2_site_8:AGLT2_site_9": {
    "bandwidth": "207.87Mbps",
    "latency": "3ms"
  },
  "AGLT2_site_8:AGLT2_site_10": {
    "bandwidth": "107.22Mbps",
    "latency": "22ms"
  },
  "AGLT2_site_8:AGLT2_site_11": {
    "bandwidth": "132.69Mbps",
    "latency": "39ms"
  },
  "AGLT2_site_8:AGLT2_site_12": {
    "bandwidth": "139.09Mbps",
    "latency": "3ms"
  },
  "AGLT2_site_8:AGLT2_site_13": {
    "bandwidth": "14.6Mbps",
    "latency": "3ms"
  },
  "AGLT2_site_8:AGLT2_site_14": {
    "bandwidth": "193.29Mbps",
    "latency": "37ms"
  },
  "AGLT2_site_8:AGLT2_site_15": {
    "bandwidth": "152.04Mbps",
    "latency": "3ms"
  },
  "AGLT2_site_8:AGLT2_site_16": {
    "bandwidth": "96.11Mbps",
    "latency": "8ms"
  },
  "AGLT2_site_8:AGLT2_site_17": {
    "bandwidth": "184.2Mbps",
    "latency": "31ms"
  },
  "AGLT2_site_8:AGLT2_site_18": {
    "bandwidth": "108.56Mbps",
    "latency": "21ms"
  },
  "AGLT2_site_8:AGLT2_site_19": {
    "bandwidth": "162.21Mbps",
    "latency": "26ms"
  },
  "AGLT2_site_8:AGLT2_site_20": {
    "bandwidth": "113.9Mbps",
    "latency": "36ms"
  },
  "AGLT2_site_8:AGLT2_site_21": {
    "bandwidth": "163.24Mbps",
    "latency": "10ms"
  },
  "AGLT2_site_8:AGLT2_site_22": {
    "bandwidth": "0.1Mbps",
    "latency": "29ms"
  },
  "AGLT2_site_8:AGLT2_site_23": {
    "bandwidth": "205.98Mbps",
    "latency": "13ms"
  },
  "AGLT2_site_8:AGLT2_site_24": {
    "bandwidth": "166.19Mbps",
    "latency": "21ms"
  },
  "AGLT2_site_8:AGLT2_site_25": {
    "bandwidth": "31.65Mbps",
    "latency": "33ms"
  },
  "AGLT2_site_8:AGLT2_site_26": {
    "bandwidth": "124.02Mbps",
    "latency": "22ms"
  },
  "AGLT2_site_8:AGLT2_site_27": {
    "bandwidth": "158.74Mbps",
    "latency": "29ms"
  },
  "AGLT2_site_8:AGLT2_site_28": {
    "bandwidth": "124.63Mbps",
    "latency": "5ms"
  },
  "AGLT2_site_8:AGLT2_site_29": {
    "bandwidth": "134.15Mbps",
    "latency": "19ms"
  },
  "AGLT2_site_8:AGLT2_site_30": {
    "bandwidth": "60.98Mbps",
    "latency": "29ms"
  },
  "AGLT2_site_8:AGLT2_site_31": {
    "bandwidth": "34.37Mbps",
    "latency": "9ms"
  },
  "AGLT2_site_9:AGLT2_site_10": {
    "bandwidth": "103.26Mbps",
    "latency": "38ms"
  },
  "AGLT2_site_9:AGLT2_site_11": {
    "bandwidth": "131.98Mbps",
    "latency": "1ms"
  },
  "AGLT2_site_9:AGLT2_site_12": {
    "bandwidth": "111.94Mbps",
    "latency": "27ms"
  },
  "AGLT2_site_9:AGLT2_site_13": {
    "bandwidth": "47.17Mbps",
    "latency": "27ms"
  },
  "AGLT2_site_9:AGLT2_site_14": {
    "bandwidth": "113.0Mbps",
    "latency": "21ms"
  },
  "AGLT2_site_9:AGLT2_site_15": {
    "bandwidth": "127.83Mbps",
    "latency": "38ms"
  },
  "AGLT2_site_9:AGLT2_site_16": {
    "bandwidth": "119.56Mbps",
    "latency": "17ms"
  },
  "AGLT2_site_9:AGLT2_site_17": {
    "bandwidth": "199.84Mbps",
    "latency": "24ms"
  },
  "AGLT2_site_9:AGLT2_site_18": {
    "bandwidth": "77.29Mbps",
    "latency": "40ms"
  },
  "AGLT2_site_9:AGLT2_site_19": {
    "bandwidth": "28.3Mbps",
    "latency": "25ms"
  },
  "AGLT2_site_9:AGLT2_site_20": {
    "bandwidth": "55.74Mbps",
    "latency": "21ms"
  },
  "AGLT2_site_9:AGLT2_site_21": {
    "bandwidth": "107.43Mbps",
    "latency": "25ms"
  },
  "AGLT2_site_9:AGLT2_site_22": {
    "bandwidth": "145.35Mbps",
    "latency": "15ms"
  },
  "AGLT2_site_9:AGLT2_site_23": {
    "bandwidth": "64.47Mbps",
    "latency": "22ms"
  },
  "AGLT2_site_9:AGLT2_site_24": {
    "bandwidth": "120.65Mbps",
    "latency": "3ms"
  },
  "AGLT2_site_9:AGLT2_site_25": {
    "bandwidth": "99.31Mbps",
    "latency": "22ms"
  },
  "AGLT2_site_9:AGLT2_site_26": {
    "bandwidth": "88.14Mbps",
    "latency": "25ms"
  },
  "AGLT2_site_9:AGLT2_site_27": {
    "bandwidth": "152.01Mbps",
    "latency": "11ms"
  },
  "AGLT2_site_9:AGLT2_site_28": {
    "bandwidth": "78.22Mbps",
    "latency": "27ms"
  },
  "AGLT2_site_9:AGLT2_site_29": {
    "bandwidth": "38.18Mbps",
    "latency": "23ms"
  },
  "AGLT2_site_9:AGLT2_site_30": {
    "bandwidth": "194.93Mbps",
    "latency": "10ms"
  },
  "AGLT2_site_9:AGLT2_site_31": {
    "bandwidth": "60.4Mbps",
    "latency": "15ms"
  },
  "AGLT2_site_10:AGLT2_site_11": {
    "bandwidth": "81.85Mbps",
    "latency": "26ms"
  },
  "AGLT2_site_10:AGLT2_site_12": {
    "bandwidth": "73.78Mbps",
    "latency": "31ms"
  },
  "AGLT2_site_10:AGLT2_site_13": {
    "bandwidth": "144.85Mbps",
    "latency": "24ms"
  },
  "AGLT2_site_10:AGLT2_site_14": {
    "bandwidth": "51.32Mbps",
    "latency": "16ms"
  },
  "AGLT2_site_10:AGLT2_site_15": {
    "bandwidth": "149.58Mbps",
    "latency": "40ms"
  },
  "AGLT2_site_10:AGLT2_site_16": {
    "bandwidth": "27.08Mbps",
    "latency": "22ms"
  },
  "AGLT2_site_10:AGLT2_site_17": {
    "bandwidth": "0.1Mbps",
    "latency": "26ms"
  },
  "AGLT2_site_10:AGLT2_site_18": {
    "bandwidth": "42.64Mbps",
    "latency": "17ms"
  },
  "AGLT2_site_10:AGLT2_site_19": {
    "bandwidth": "47.57Mbps",
    "latency": "22ms"
  },
  "AGLT2_site_10:AGLT2_site_20": {
    "bandwidth": "209.96Mbps",
    "latency": "4ms"
  },
  "AGLT2_site_10:AGLT2_site_21": {
    "bandwidth": "46.88Mbps",
    "latency": "22ms"
  },
  "AGLT2_site_10:AGLT2_site_22": {
    "bandwidth": "167.77Mbps",
    "latency": "39ms"
  },
  "AGLT2_site_10:AGLT2_site_23": {
    "bandwidth": "209.67Mbps",
    "latency": "30ms"
  },
  "AGLT2_site_10:AGLT2_site_24": {
    "bandwidth": "21.24Mbps",
    "latency": "11ms"
  },
  "AGLT2_site_10:AGLT2_site_25": {
    "bandwidth": "71.38Mbps",
    "latency": "9ms"
  },
  "AGLT2_site_10:AGLT2_site_26": {
    "bandwidth": "67.8Mbps",
    "latency": "28ms"
  },
  "AGLT2_site_10:AGLT2_site_27": {
    "bandwidth": "36.46Mbps",
    "latency": "27ms"
  },
  "AGLT2_site_10:AGLT2_site_28": {
    "bandwidth": "87.83Mbps",
    "latency": "23ms"
  },
  "AGLT2_site_10:AGLT2_site_29": {
    "bandwidth": "0.1Mbps",
    "latency": "12ms"
  },
  "AGLT2_site_10:AGLT2_site_30": {
    "bandwidth": "114.62Mbps",
    "latency": "37ms"
  },
  "AGLT2_site_10:AGLT2_site_31": {
    "bandwidth": "86.33Mbps",
    "latency": "17ms"
  },
  "AGLT2_site_11:AGLT2_site_12": {
    "bandwidth": "36.9Mbps",
    "latency": "9ms"
  },
  "AGLT2_site_11:AGLT2_site_13": {
    "bandwidth": "226.94Mbps",
    "latency": "19ms"
  },
  "AGLT2_site_11:AGLT2_site_14": {
    "bandwidth": "91.0Mbps",
    "latency": "25ms"
  },
  "AGLT2_site_11:AGLT2_site_15": {
    "bandwidth": "175.05Mbps",
    "latency": "12ms"
  },
  "AGLT2_site_11:AGLT2_site_16": {
    "bandwidth": "113.64Mbps",
    "latency": "2ms"
  },
  "AGLT2_site_11:AGLT2_site_17": {
    "bandwidth": "117.12Mbps",
    "latency": "28ms"
  },
  "AGLT2_site_11:AGLT2_site_18": {
    "bandwidth": "5.87Mbps",
    "latency": "32ms"
  },
  "AGLT2_site_11:AGLT2_site_19": {
    "bandwidth": "104.69Mbps",
    "latency": "13ms"
  },
  "AGLT2_site_11:AGLT2_site_20": {
    "bandwidth": "69.14Mbps",
    "latency": "37ms"
  },
  "AGLT2_site_11:AGLT2_site_21": {
    "bandwidth": "116.81Mbps",
    "latency": "36ms"
  },
  "AGLT2_site_11:AGLT2_site_22": {
    "bandwidth": "84.4Mbps",
    "latency": "13ms"
  },
  "AGLT2_site_11:AGLT2_site_23": {
    "bandwidth": "46.55Mbps",
    "latency": "28ms"
  },
  "AGLT2_site_11:AGLT2_site_24": {
    "bandwidth": "18.85Mbps",
    "latency": "20ms"
  },
  "AGLT2_site_11:AGLT2_site_25": {
    "bandwidth": "173.08Mbps",
    "latency": "23ms"
  },
  "AGLT2_site_11:AGLT2_site_26": {
    "bandwidth": "157.71Mbps",
    "latency": "18ms"
  },
  "AGLT2_site_11:AGLT2_site_27": {
    "bandwidth": "95.43Mbps",
    "latency": "20ms"
  },
  "AGLT2_site_11:AGLT2_site_28": {
    "bandwidth": "114.31Mbps",
    "latency": "20ms"
  },
  "AGLT2_site_11:AGLT2_site_29": {
    "bandwidth": "99.27Mbps",
    "latency": "26ms"
  },
  "AGLT2_site_11:AGLT2_site_30": {
    "bandwidth": "54.54Mbps",
    "latency": "10ms"
  },
  "AGLT2_site_11:AGLT2_site_31": {
    "bandwidth": "145.89Mbps",
    "latency": "37ms"
  },
  "AGLT2_site_12:AGLT2_site_13": {
    "bandwidth": "102.64Mbps",
    "latency": "13ms"
  },
  "AGLT2_site_12:AGLT2_site_14": {
    "bandwidth": "0.1Mbps",
    "latency": "39ms"
  },
  "AGLT2_site_12:AGLT2_site_15": {
    "bandwidth": "30.56Mbps",
    "latency": "21ms"
  },
  "AGLT2_site_12:AGLT2_site_16": {
    "bandwidth": "79.61Mbps",
    "latency": "5ms"
  },
  "AGLT2_site_12:AGLT2_site_17": {
    "bandwidth": "173.97Mbps",
    "latency": "25ms"
  },
  "AGLT2_site_12:AGLT2_site_18": {
    "bandwidth": "113.09Mbps",
    "latency": "4ms"
  },
  "AGLT2_site_12:AGLT2_site_19": {
    "bandwidth": "9.45Mbps",
    "latency": "32ms"
  },
  "AGLT2_site_12:AGLT2_site_20": {
    "bandwidth": "5.54Mbps",
    "latency": "30ms"
  },
  "AGLT2_site_12:AGLT2_site_21": {
    "bandwidth": "121.87Mbps",
    "latency": "12ms"
  },
  "AGLT2_site_12:AGLT2_site_22": {
    "bandwidth": "137.69Mbps",
    "latency": "24ms"
  },
  "AGLT2_site_12:AGLT2_site_23": {
    "bandwidth": "59.7Mbps",
    "latency": "6ms"
  },
  "AGLT2_site_12:AGLT2_site_24": {
    "bandwidth": "111.02Mbps",
    "latency": "1ms"
  },
  "AGLT2_site_12:AGLT2_site_25": {
    "bandwidth": "88.26Mbps",
    "latency": "38ms"
  },
  "AGLT2_site_12:AGLT2_site_26": {
    "bandwidth": "61.51Mbps",
    "latency": "21ms"
  },
  "AGLT2_site_12:AGLT2_site_27": {
    "bandwidth": "166.85Mbps",
    "latency": "21ms"
  },
  "AGLT2_site_12:AGLT2_site_28": {
    "bandwidth": "0.1Mbps",
    "latency": "33ms"
  },
  "AGLT2_site_12:AGLT2_site_29": {
    "bandwidth": "139.1Mbps",
    "latency": "6ms"
  },
  "AGLT2_site_12:AGLT2_site_30": {
    "bandwidth": "107.89Mbps",
    "latency": "34ms"
  },
  "AGLT2_site_12:AGLT2_site_31": {
    "bandwidth": "21.14Mbps",
    "latency": "5ms"
  },
  "AGLT2_site_13:AGLT2_site_14": {
    "bandwidth": "109.08Mbps",
    "latency": "24ms"
  },
  "AGLT2_site_13:AGLT2_site_15": {
    "bandwidth": "143.1Mbps",
    "latency": "7ms"
  },
  "AGLT2_site_13:AGLT2_site_16": {
    "bandwidth": "155.16Mbps",
    "latency": "2ms"
  },
  "AGLT2_site_13:AGLT2_site_17": {
    "bandwidth": "163.3Mbps",
    "latency": "2ms"
  },
  "AGLT2_site_13:AGLT2_site_18": {
    "bandwidth": "115.47Mbps",
    "latency": "26ms"
  },
  "AGLT2_site_13:AGLT2_site_19": {
    "bandwidth": "33.96Mbps",
    "latency": "7ms"
  },
  "AGLT2_site_13:AGLT2_site_20": {
    "bandwidth": "135.83Mbps",
    "latency": "20ms"
  },
  "AGLT2_site_13:AGLT2_site_21": {
    "bandwidth": "56.55Mbps",
    "latency": "20ms"
  },
  "AGLT2_site_13:AGLT2_site_22": {
    "bandwidth": "101.51Mbps",
    "latency": "13ms"
  },
  "AGLT2_site_13:AGLT2_site_23": {
    "bandwidth": "153.59Mbps",
    "latency": "28ms"
  },
  "AGLT2_site_13:AGLT2_site_24": {
    "bandwidth": "103.83Mbps",
    "latency": "26ms"
  },
  "AGLT2_site_13:AGLT2_site_25": {
    "bandwidth": "143.41Mbps",
    "latency": "10ms"
  },
  "AGLT2_site_13:AGLT2_site_26": {
    "bandwidth": "27.3Mbps",
    "latency": "11ms"
  },
  "AGLT2_site_13:AGLT2_site_27": {
    "bandwidth": "96.89Mbps",
    "latency": "15ms"
  },
  "AGLT2_site_13:AGLT2_site_28": {
    "bandwidth": "32.68Mbps",
    "latency": "24ms"
  },
  "AGLT2_site_13:AGLT2_site_29": {
    "bandwidth": "33.07Mbps",
    "latency": "39ms"
  },
  "AGLT2_site_13:AGLT2_site_30": {
    "bandwidth": "131.36Mbps",
    "latency": "30ms"
  },
  "AGLT2_site_13:AGLT2_site_31": {
    "bandwidth": "97.34Mbps",
    "latency": "11ms"
  },
  "AGLT2_site_14:AGLT2_site_15": {
    "bandwidth": "84.9Mbps",
    "latency": "24ms"
  },
  "AGLT2_site_14:AGLT2_site_16": {
    "bandwidth": "135.16Mbps",
    "latency": "12ms"
  },
  "AGLT2_site_14:AGLT2_site_17": {
    "bandwidth": "116.07Mbps",
    "latency": "14ms"
  },
  "AGLT2_site_14:AGLT2_site_18": {
    "bandwidth": "102.48Mbps",
    "latency": "4ms"
  },
  "AGLT2_site_14:AGLT2_site_19": {
    "bandwidth": "68.56Mbps",
    "latency": "23ms"
  },
  "AGLT2_site_14:AGLT2_site_20": {
    "bandwidth": "87.31Mbps",
    "latency": "32ms"
  },
  "AGLT2_site_14:AGLT2_site_21": {
    "bandwidth": "145.44Mbps",
    "latency": "30ms"
  },
  "AGLT2_site_14:AGLT2_site_22": {
    "bandwidth": "141.35Mbps",
    "latency": "9ms"
  },
  "AGLT2_site_14:AGLT2_site_23": {
    "bandwidth": "175.12Mbps",
    "latency": "30ms"
  },
  "AGLT2_site_14:AGLT2_site_24": {
    "bandwidth": "259.3Mbps",
    "latency": "9ms"
  },
  "AGLT2_site_14:AGLT2_site_25": {
    "bandwidth": "81.27Mbps",
    "latency": "27ms"
  },
  "AGLT2_site_14:AGLT2_site_26": {
    "bandwidth": "77.41Mbps",
    "latency": "25ms"
  },
  "AGLT2_site_14:AGLT2_site_27": {
    "bandwidth": "173.88Mbps",
    "latency": "12ms"
  },
  "AGLT2_site_14:AGLT2_site_28": {
    "bandwidth": "133.2Mbps",
    "latency": "18ms"
  },
  "AGLT2_site_14:AGLT2_site_29": {
    "bandwidth": "39.85Mbps",
    "latency": "25ms"
  },
  "AGLT2_site_14:AGLT2_site_30": {
    "bandwidth": "6.09Mbps",
    "latency": "3ms"
  },
  "AGLT2_site_14:AGLT2_site_31": {
    "bandwidth": "66.13Mbps",
    "latency": "38ms"
  },
  "AGLT2_site_15:AGLT2_site_16": {
    "bandwidth": "17.84Mbps",
    "latency": "33ms"
  },
  "AGLT2_site_15:AGLT2_site_17": {
    "bandwidth": "172.25Mbps",
    "latency": "16ms"
  },
  "AGLT2_site_15:AGLT2_site_18": {
    "bandwidth": "84.52Mbps",
    "latency": "7ms"
  },
  "AGLT2_site_15:AGLT2_site_19": {
    "bandwidth": "114.12Mbps",
    "latency": "32ms"
  },
  "AGLT2_site_15:AGLT2_site_20": {
    "bandwidth": "95.26Mbps",
    "latency": "32ms"
  },
  "AGLT2_site_15:AGLT2_site_21": {
    "bandwidth": "93.79Mbps",
    "latency": "10ms"
  },
  "AGLT2_site_15:AGLT2_site_22": {
    "bandwidth": "95.85Mbps",
    "latency": "33ms"
  },
  "AGLT2_site_15:AGLT2_site_23": {
    "bandwidth": "192.05Mbps",
    "latency": "39ms"
  },
  "AGLT2_site_15:AGLT2_site_24": {
    "bandwidth": "0.1Mbps",
    "latency": "24ms"
  },
  "AGLT2_site_15:AGLT2_site_25": {
    "bandwidth": "245.68Mbps",
    "latency": "26ms"
  },
  "AGLT2_site_15:AGLT2_site_26": {
    "bandwidth": "107.92Mbps",
    "latency": "37ms"
  },
  "AGLT2_site_15:AGLT2_site_27": {
    "bandwidth": "137.4Mbps",
    "latency": "12ms"
  },
  "AGLT2_site_15:AGLT2_site_28": {
    "bandwidth": "15.95Mbps",
    "latency": "5ms"
  },
  "AGLT2_site_15:AGLT2_site_29": {
    "bandwidth": "137.57Mbps",
    "latency": "36ms"
  },
  "AGLT2_site_15:AGLT2_site_30": {
    "bandwidth": "133.0Mbps",
    "latency": "22ms"
  },
  "AGLT2_site_15:AGLT2_site_31": {
    "bandwidth": "118.43Mbps",
    "latency": "22ms"
  },
  "AGLT2_site_16:AGLT2_site_17": {
    "bandwidth": "28.58Mbps",
    "latency": "35ms"
  },
  "AGLT2_site_16:AGLT2_site_18": {
    "bandwidth": "155.34Mbps",
    "latency": "35ms"
  },
  "AGLT2_site_16:AGLT2_site_19": {
    "bandwidth": "186.19Mbps",
    "latency": "34ms"
  },
  "AGLT2_site_16:AGLT2_site_20": {
    "bandwidth": "133.28Mbps",
    "latency": "8ms"
  },
  "AGLT2_site_16:AGLT2_site_21": {
    "bandwidth": "100.48Mbps",
    "latency": "32ms"
  },
  "AGLT2_site_16:AGLT2_site_22": {
    "bandwidth": "58.41Mbps",
    "latency": "16ms"
  },
  "AGLT2_site_16:AGLT2_site_23": {
    "bandwidth": "38.17Mbps",
    "latency": "32ms"
  },
  "AGLT2_site_16:AGLT2_site_24": {
    "bandwidth": "87.37Mbps",
    "latency": "10ms"
  },
  "AGLT2_site_16:AGLT2_site_25": {
    "bandwidth": "118.95Mbps",
    "latency": "17ms"
  },
  "AGLT2_site_16:AGLT2_site_26": {
    "bandwidth": "115.02Mbps",
    "latency": "30ms"
  },
  "AGLT2_site_16:AGLT2_site_27": {
    "bandwidth": "65.7Mbps",
    "latency": "37ms"
  },
  "AGLT2_site_16:AGLT2_site_28": {
    "bandwidth": "151.49Mbps",
    "latency": "22ms"
  },
  "AGLT2_site_16:AGLT2_site_29": {
    "bandwidth": "103.67Mbps",
    "latency": "38ms"
  },
  "AGLT2_site_16:AGLT2_site_30": {
    "bandwidth": "211.46Mbps",
    "latency": "23ms"
  },
  "AGLT2_site_16:AGLT2_site_31": {
    "bandwidth": "122.79Mbps",
    "latency": "22ms"
  },
  "AGLT2_site_17:AGLT2_site_18": {
    "bandwidth": "101.9Mbps",
    "latency": "9ms"
  },
  "AGLT2_site_17:AGLT2_site_19": {
    "bandwidth": "158.75Mbps",
    "latency": "17ms"
  },
  "AGLT2_site_17:AGLT2_site_20": {
    "bandwidth": "69.83Mbps",
    "latency": "30ms"
  },
  "AGLT2_site_17:AGLT2_site_21": {
    "bandwidth": "111.05Mbps",
    "latency": "21ms"
  },
  "AGLT2_site_17:AGLT2_site_22": {
    "bandwidth": "39.31Mbps",
    "latency": "26ms"
  },
  "AGLT2_site_17:AGLT2_site_23": {
    "bandwidth": "64.47Mbps",
    "latency": "31ms"
  },
  "AGLT2_site_17:AGLT2_site_24": {
    "bandwidth": "134.84Mbps",
    "latency": "36ms"
  },
  "AGLT2_site_17:AGLT2_site_25": {
    "bandwidth": "145.43Mbps",
    "latency": "13ms"
  },
  "AGLT2_site_17:AGLT2_site_26": {
    "bandwidth": "164.24Mbps",
    "latency": "34ms"
  },
  "AGLT2_site_17:AGLT2_site_27": {
    "bandwidth": "184.24Mbps",
    "latency": "4ms"
  },
  "AGLT2_site_17:AGLT2_site_28": {
    "bandwidth": "80.11Mbps",
    "latency": "23ms"
  },
  "AGLT2_site_17:AGLT2_site_29": {
    "bandwidth": "195.4Mbps",
    "latency": "5ms"
  },
  "AGLT2_site_17:AGLT2_site_30": {
    "bandwidth": "91.52Mbps",
    "latency": "29ms"
  },
  "AGLT2_site_17:AGLT2_site_31": {
    "bandwidth": "119.69Mbps",
    "latency": "28ms"
  },
  "AGLT2_site_18:AGLT2_site_19": {
    "bandwidth": "182.9Mbps",
    "latency": "39ms"
  },
  "AGLT2_site_18:AGLT2_site_20": {
    "bandwidth": "166.75Mbps",
    "latency": "29ms"
  },
  "AGLT2_site_18:AGLT2_site_21": {
    "bandwidth": "89.52Mbps",
    "latency": "8ms"
  },
  "AGLT2_site_18:AGLT2_site_22": {
    "bandwidth": "115.7Mbps",
    "latency": "16ms"
  },
  "AGLT2_site_18:AGLT2_site_23": {
    "bandwidth": "93.67Mbps",
    "latency": "5ms"
  },
  "AGLT2_site_18:AGLT2_site_24": {
    "bandwidth": "151.62Mbps",
    "latency": "2ms"
  },
  "AGLT2_site_18:AGLT2_site_25": {
    "bandwidth": "64.14Mbps",
    "latency": "13ms"
  },
  "AGLT2_site_18:AGLT2_site_26": {
    "bandwidth": "116.16Mbps",
    "latency": "2ms"
  },
  "AGLT2_site_18:AGLT2_site_27": {
    "bandwidth": "147.95Mbps",
    "latency": "14ms"
  },
  "AGLT2_site_18:AGLT2_site_28": {
    "bandwidth": "85.8Mbps",
    "latency": "34ms"
  },
  "AGLT2_site_18:AGLT2_site_29": {
    "bandwidth": "64.95Mbps",
    "latency": "24ms"
  },
  "AGLT2_site_18:AGLT2_site_30": {
    "bandwidth": "128.96Mbps",
    "latency": "39ms"
  },
  "AGLT2_site_18:AGLT2_site_31": {
    "bandwidth": "96.92Mbps",
    "latency": "26ms"
  },
  "AGLT2_site_19:AGLT2_site_20": {
    "bandwidth": "0.1Mbps",
    "latency": "29ms"
  },
  "AGLT2_site_19:AGLT2_site_21": {
    "bandwidth": "60.91Mbps",
    "latency": "2ms"
  },
  "AGLT2_site_19:AGLT2_site_22": {
    "bandwidth": "125.88Mbps",
    "latency": "3ms"
  },
  "AGLT2_site_19:AGLT2_site_23": {
    "bandwidth": "122.12Mbps",
    "latency": "17ms"
  },
  "AGLT2_site_19:AGLT2_site_24": {
    "bandwidth": "128.56Mbps",
    "latency": "1ms"
  },
  "AGLT2_site_19:AGLT2_site_25": {
    "bandwidth": "120.89Mbps",
    "latency": "10ms"
  },
  "AGLT2_site_19:AGLT2_site_26": {
    "bandwidth": "117.24Mbps",
    "latency": "33ms"
  },
  "AGLT2_site_19:AGLT2_site_27": {
    "bandwidth": "122.84Mbps",
    "latency": "38ms"
  },
  "AGLT2_site_19:AGLT2_site_28": {
    "bandwidth": "19.09Mbps",
    "latency": "30ms"
  },
  "AGLT2_site_19:AGLT2_site_29": {
    "bandwidth": "175.52Mbps",
    "latency": "28ms"
  },
  "AGLT2_site_19:AGLT2_site_30": {
    "bandwidth": "28.66Mbps",
    "latency": "17ms"
  },
  "AGLT2_site_19:AGLT2_site_31": {
    "bandwidth": "27.09Mbps",
    "latency": "11ms"
  },
  "AGLT2_site_20:AGLT2_site_21": {
    "bandwidth": "97.4Mbps",
    "latency": "7ms"
  },
  "AGLT2_site_20:AGLT2_site_22": {
    "bandwidth": "0.1Mbps",
    "latency": "24ms"
  },
  "AGLT2_site_20:AGLT2_site_23": {
    "bandwidth": "140.75Mbps",
    "latency": "4ms"
  },
  "AGLT2_site_20:AGLT2_site_24": {
    "bandwidth": "110.32Mbps",
    "latency": "22ms"
  },
  "AGLT2_site_20:AGLT2_site_25": {
    "bandwidth": "105.17Mbps",
    "latency": "38ms"
  },
  "AGLT2_site_20:AGLT2_site_26": {
    "bandwidth": "201.71Mbps",
    "latency": "5ms"
  },
  "AGLT2_site_20:AGLT2_site_27": {
    "bandwidth": "160.9Mbps",
    "latency": "3ms"
  },
  "AGLT2_site_20:AGLT2_site_28": {
    "bandwidth": "104.0Mbps",
    "latency": "25ms"
  },
  "AGLT2_site_20:AGLT2_site_29": {
    "bandwidth": "62.43Mbps",
    "latency": "28ms"
  },
  "AGLT2_site_20:AGLT2_site_30": {
    "bandwidth": "59.7Mbps",
    "latency": "11ms"
  },
  "AGLT2_site_20:AGLT2_site_31": {
    "bandwidth": "30.3Mbps",
    "latency": "24ms"
  },
  "AGLT2_site_21:AGLT2_site_22": {
    "bandwidth": "147.65Mbps",
    "latency": "13ms"
  },
  "AGLT2_site_21:AGLT2_site_23": {
    "bandwidth": "48.4Mbps",
    "latency": "28ms"
  },
  "AGLT2_site_21:AGLT2_site_24": {
    "bandwidth": "75.84Mbps",
    "latency": "38ms"
  },
  "AGLT2_site_21:AGLT2_site_25": {
    "bandwidth": "6.15Mbps",
    "latency": "12ms"
  },
  "AGLT2_site_21:AGLT2_site_26": {
    "bandwidth": "101.54Mbps",
    "latency": "11ms"
  },
  "AGLT2_site_21:AGLT2_site_27": {
    "bandwidth": "63.53Mbps",
    "latency": "20ms"
  },
  "AGLT2_site_21:AGLT2_site_28": {
    "bandwidth": "142.84Mbps",
    "latency": "33ms"
  },
  "AGLT2_site_21:AGLT2_site_29": {
    "bandwidth": "136.52Mbps",
    "latency": "15ms"
  },
  "AGLT2_site_21:AGLT2_site_30": {
    "bandwidth": "122.13Mbps",
    "latency": "10ms"
  },
  "AGLT2_site_21:AGLT2_site_31": {
    "bandwidth": "85.3Mbps",
    "latency": "10ms"
  },
  "AGLT2_site_22:AGLT2_site_23": {
    "bandwidth": "171.19Mbps",
    "latency": "2ms"
  },
  "AGLT2_site_22:AGLT2_site_24": {
    "bandwidth": "29.16Mbps",
    "latency": "8ms"
  },
  "AGLT2_site_22:AGLT2_site_25": {
    "bandwidth": "146.34Mbps",
    "latency": "39ms"
  },
  "AGLT2_site_22:AGLT2_site_26": {
    "bandwidth": "226.06Mbps",
    "latency": "7ms"
  },
  "AGLT2_site_22:AGLT2_site_27": {
    "bandwidth": "62.8Mbps",
    "latency": "26ms"
  },
  "AGLT2_site_22:AGLT2_site_28": {
    "bandwidth": "7.28Mbps",
    "latency": "18ms"
  },
  "AGLT2_site_22:AGLT2_site_29": {
    "bandwidth": "82.2Mbps",
    "latency": "9ms"
  },
  "AGLT2_site_22:AGLT2_site_30": {
    "bandwidth": "66.32Mbps",
    "latency": "38ms"
  },
  "AGLT2_site_22:AGLT2_site_31": {
    "bandwidth": "86.3Mbps",
    "latency": "6ms"
  },
  "AGLT2_site_23:AGLT2_site_24": {
    "bandwidth": "116.08Mbps",
    "latency": "7ms"
  },
  "AGLT2_site_23:AGLT2_site_25": {
    "bandwidth": "208.93Mbps",
    "latency": "37ms"
  },
  "AGLT2_site_23:AGLT2_site_26": {
    "bandwidth": "105.38Mbps",
    "latency": "28ms"
  },
  "AGLT2_site_23:AGLT2_site_27": {
    "bandwidth": "106.49Mbps",
    "latency": "26ms"
  },
  "AGLT2_site_23:AGLT2_site_28": {
    "bandwidth": "126.49Mbps",
    "latency": "36ms"
  },
  "AGLT2_site_23:AGLT2_site_29": {
    "bandwidth": "164.09Mbps",
    "latency": "5ms"
  },
  "AGLT2_site_23:AGLT2_site_30": {
    "bandwidth": "74.37Mbps",
    "latency": "28ms"
  },
  "AGLT2_site_23:AGLT2_site_31": {
    "bandwidth": "115.93Mbps",
    "latency": "8ms"
  },
  "AGLT2_site_24:AGLT2_site_25": {
    "bandwidth": "112.01Mbps",
    "latency": "15ms"
  },
  "AGLT2_site_24:AGLT2_site_26": {
    "bandwidth": "133.1Mbps",
    "latency": "11ms"
  },
  "AGLT2_site_24:AGLT2_site_27": {
    "bandwidth": "5.75Mbps",
    "latency": "22ms"
  },
  "AGLT2_site_24:AGLT2_site_28": {
    "bandwidth": "44.17Mbps",
    "latency": "30ms"
  },
  "AGLT2_site_24:AGLT2_site_29": {
    "bandwidth": "205.96Mbps",
    "latency": "40ms"
  },
  "AGLT2_site_24:AGLT2_site_30": {
    "bandwidth": "101.13Mbps",
    "latency": "21ms"
  },
  "AGLT2_site_24:AGLT2_site_31": {
    "bandwidth": "127.44Mbps",
    "latency": "30ms"
  },
  "AGLT2_site_25:AGLT2_site_26": {
    "bandwidth": "83.47Mbps",
    "latency": "6ms"
  },
  "AGLT2_site_25:AGLT2_site_27": {
    "bandwidth": "25.95Mbps",
    "latency": "37ms"
  },
  "AGLT2_site_25:AGLT2_site_28": {
    "bandwidth": "171.41Mbps",
    "latency": "19ms"
  },
  "AGLT2_site_25:AGLT2_site_29": {
    "bandwidth": "157.39Mbps",
    "latency": "31ms"
  },
  "AGLT2_site_25:AGLT2_site_30": {
    "bandwidth": "165.03Mbps",
    "latency": "24ms"
  },
  "AGLT2_site_25:AGLT2_site_31": {
    "bandwidth": "111.11Mbps",
    "latency": "15ms"
  },
  "AGLT2_site_26:AGLT2_site_27": {
    "bandwidth": "82.38Mbps",
    "latency": "33ms"
  },
  "AGLT2_site_26:AGLT2_site_28": {
    "bandwidth": "6.76Mbps",
    "latency": "34ms"
  },
  "AGLT2_site_26:AGLT2_site_29": {
    "bandwidth": "157.49Mbps",
    "latency": "18ms"
  },
  "AGLT2_site_26:AGLT2_site_30": {
    "bandwidth": "181.86Mbps",
    "latency": "37ms"
  },
  "AGLT2_site_26:AGLT2_site_31": {
    "bandwidth": "32.98Mbps",
    "latency": "36ms"
  },
  "AGLT2_site_27:AGLT2_site_28": {
    "bandwidth": "170.2Mbps",
    "latency": "29ms"
  },
  "AGLT2_site_27:AGLT2_site_29": {
    "bandwidth": "134.66Mbps",
    "latency": "6ms"
  },
  "AGLT2_site_27:AGLT2_site_30": {
    "bandwidth": "0.1Mbps",
    "latency": "37ms"
  },
  "AGLT2_site_27:AGLT2_site_31": {
    "bandwidth": "71.87Mbps",
    "latency": "18ms"
  },
  "AGLT2_site_28:AGLT2_site_29": {
    "bandwidth": "98.98Mbps",
    "latency": "27ms"
  },
  "AGLT2_site_28:AGLT2_site_30": {
    "bandwidth": "110.03Mbps",
    "latency": "17ms"
  },
  "AGLT2_site_28:AGLT2_site_31": {
    "bandwidth": "68.74Mbps",
    "latency": "6ms"
  },
  "AGLT2_site_29:AGLT2_site_30": {
    "bandwidth": "15.55Mbps",
    "latency": "15ms"
  },
  "AGLT2_site_29:AGLT2_site_31": {
    "bandwidth": "117.38Mbps",
    "latency": "28ms"
  },
  "AGLT2_site_30:AGLT2_site_31": {
    "bandwidth": "141.12Mbps",
    "latency": "26ms"
  }
}